voly/__init__.py
voly/client.py
voly/exceptions.py
voly/formulas.py
voly/models.py
voly/core/__init__.py
voly/core/charts.py
voly/core/data.py
voly/core/fit.py
voly/core/hd.py
voly/core/interpolate.py
voly/core/rnd.py
voly/utils/__init__.py
voly/utils/density.py
voly/utils/logger.py
voly-0.0.261.dist-info/licenses/LICENSE
voly-0.0.261.dist-info/METADATA
voly-0.0.261.dist-info/WHEEL
voly-0.0.261.dist-info/top_level.txt
voly-0.0.261.dist-info/RECORD
